LICENSE
MANIFEST.in
setup.cfg
setup.py
offlinemot/__init__.py
offlinemot/background_subtraction.py
offlinemot/config.py
offlinemot/core.py
offlinemot/detection.py
offlinemot/fix_view.py
offlinemot/objects_classes.py
offlinemot/post_process.py
offlinemot/show_results.py
offlinemot/utils_.py
offlinemot.egg-info/PKG-INFO
offlinemot.egg-info/SOURCES.txt
offlinemot.egg-info/dependency_links.txt
offlinemot.egg-info/requires.txt
offlinemot.egg-info/top_level.txt
offlinemot/model/config.ini
offlinemot/model/goturn.prototxt
offlinemot/model/obj.names
offlinemot/model/sample.mp4
offlinemot/model/sample.mp4.txt
offlinemot/model/sample.txt
offlinemot/model/yolov4-obj.cfg
offlinemot/tests/__init__.py
offlinemot/tests/example_data.py
offlinemot/tests/test_background_subtraction.py
offlinemot/tests/test_core.py
offlinemot/tests/test_detection.py
offlinemot/tests/test_fix_view.py
offlinemot/tests/test_objects_classes.py
offlinemot/tests/test_post_process.py
offlinemot/tests/test_utils_.py
offlinemot/tool/__init__.py
offlinemot/tool/config.py
offlinemot/tool/darknet2pytorch.py
offlinemot/tool/region_loss.py
offlinemot/tool/torch_utils.py
offlinemot/tool/utils.py
offlinemot/tool/yolo_layer.py