Metadata-Version: 2.1
Name: offlinemot
Version: 1.2.1
Home-page: https://github.com/engyasin/Offline_MOT
Download-URL: https://github.com/engyasin/Offline_MOT/archive/refs/tags/v1.2.1.tar.gz
Author: Yasin Yousif
Author-email: mrhidestev@hotmail.com
License: MIT
Keywords: Multi Objects Tracking,Detection,Traffic Data
Classifier: Development Status :: 3 - Alpha
Classifier: Intended Audience :: Developers
Classifier: Topic :: Software Development :: Build Tools
Classifier: License :: OSI Approved :: MIT License
Classifier: Programming Language :: Python :: 3
Classifier: Programming Language :: Python :: 3.4
Classifier: Programming Language :: Python :: 3.5
Classifier: Programming Language :: Python :: 3.6
License-File: LICENSE
